mux/__init__.py
mux/handler.py
mux/highlight.py
mux/progressbar.py
mux_handler-0.1.dist-info/DESCRIPTION.rst
mux_handler-0.1.dist-info/METADATA
mux_handler-0.1.dist-info/RECORD
mux_handler-0.1.dist-info/WHEEL
mux_handler-0.1.dist-info/metadata.json
mux_handler-0.1.dist-info/top_level.txt
