Metadata-Version: 2.0
Name: mux-handler
Version: 0.1
Summary: an elegant handler for python terminal logging
Home-page: https://github.com/neo1218/mux
Author: neo1218
Author-email: neo1218@yeah.net
License: MIT
Platform: any
Classifier: Intended Audience :: Developers
Classifier: License :: OSI Approved :: MIT License
Classifier: Operating System :: OS Independent
Classifier: Programming Language :: Python
Classifier: Topic :: Internet :: WWW/HTTP :: Dynamic Content
Classifier: Topic :: Software Development :: Libraries :: Python Modules
Requires-Dist: pygments
